LICENSE
MANIFEST.in
README.rst
setup.py
django_trix.egg-info/PKG-INFO
django_trix.egg-info/SOURCES.txt
django_trix.egg-info/dependency_links.txt
django_trix.egg-info/top_level.txt
trix/__init__.py
trix/admin.py
trix/fields.py
trix/urls.py
trix/views.py
trix/widgets.py
trix/static/trix/trix-core.js
trix/static/trix/trix-django.js
trix/static/trix/trix.css
trix/static/trix/trix.js