Metadata-Version: 1.1
Name: django-trix
Version: 0.3.0
Summary: Trix rich text editor widget for Django
Home-page: https://github.com/istrategylabs/django-trix
Author: Jeremy Carbaugh
Author-email: jeremy@isl.co
License: BSD
Platform: any
Classifier: Development Status :: 4 - Beta
Classifier: Environment :: Web Environment
Classifier: Framework :: Django
Classifier: Intended Audience :: Developers
Classifier: Operating System :: OS Independent
Classifier: Programming Language :: Python
Classifier: Topic :: Software Development :: Libraries :: Python Modules
